billingplatform/__init__.py
billingplatform/api.py
billingplatform/exceptions.py
billingplatform-0.3.0.dist-info/licenses/LICENSE
billingplatform-0.3.0.dist-info/METADATA
billingplatform-0.3.0.dist-info/WHEEL
billingplatform-0.3.0.dist-info/top_level.txt
billingplatform-0.3.0.dist-info/RECORD
