Metadata-Version: 2.4
Name: billingplatform
Version: 0.3.0
Summary: A community driven Python library for working with BillingPlatform APIs.
Author-email: forgineer <blake.phillips86@gmail.com>
License-Expression: Apache-2.0
Project-URL: Homepage, https://github.com/forgineer/billingplatform-py
Project-URL: Documentation, https://github.com/forgineer/billingplatform-py
Project-URL: Repository, https://github.com/forgineer/billingplatform-py
Project-URL: Issues, https://github.com/forgineer/billingplatform-py/issues
Keywords: billingplatform,rest api,billing,revenue management
Classifier: Development Status :: 3 - Alpha
Classifier: Operating System :: OS Independent
Classifier: Intended Audience :: Developers
Classifier: Topic :: Office/Business :: Financial
Classifier: Programming Language :: Python :: 3.11
Classifier: Programming Language :: Python :: 3.12
Classifier: Programming Language :: Python :: 3.13
Requires-Python: >=3.11
License-File: LICENSE
Requires-Dist: requests
Provides-Extra: mock-server
Requires-Dist: flask; extra == "mock-server"
Provides-Extra: deploy-tools
Requires-Dist: build; extra == "deploy-tools"
Requires-Dist: twine; extra == "deploy-tools"
Dynamic: license-file
